<?xml version="1.0" encoding="UTF-8"?><!--
		Taxonomy: 2019-03-27 (Final)
		********************** 
        Copyright (c) 2019 IFRS Foundation
        All rights reserved. Reproduction and use rights are strictly limited.
		For more information on the IFRS Foundation's copyright and the terms and conditions of use for these files, please refer to http://go.ifrs.org/IFRSTterms.
		The IFRS Foundation has trade marks registered around the world (Marks) including 'IAS', 'IASB', the IASB logo, 'IFRIC', 'IFRS', the IFRS logo, 'IFRS for SMEs', the IFRS for SMEs logo, the 'Hexagon Device', 'International Accounting Standards', 'International Financial Reporting Standards', 'NIIF' and 'SIC'. Further details of the IFRS Foundation's Marks are available from the IFRS Foundation on request.
        **********************
--><link:linkbase xmlns:link="http://www.xbrl.org/2003/linkbase" xmlns:xlink="http://www.w3.org/1999/xlink" xmlns:xsi="http://www.w3.org/2001/XMLSchema-instance" xsi:schemaLocation="http://www.xbrl.org/2003/linkbase http://www.xbrl.org/2003/xbrl-linkbase-2003-12-31.xsd">
  <link:roleRef roleURI="http://xbrl.ifrs.org/role/ifrs/ias_7_2019-03-27_role-800300" xlink:href="rol_ias_7_2019-03-27.xsd#ias_7_2019-03-27_role-800300" xlink:type="simple"/>
  <link:presentationLink xlink:role="http://xbrl.ifrs.org/role/ifrs/ias_7_2019-03-27_role-800300" xlink:type="extended">
    <link:loc xlink:href="../../full_ifrs-cor_2019-03-27.xsd#ifrs-full_CashFlowsFromUsedInOperatingActivitiesAbstract" xlink:label="loc_1" xlink:type="locator"/>
    <link:loc xlink:href="../../full_ifrs-cor_2019-03-27.xsd#ifrs-full_StatementOfCashFlowsAbstract" xlink:label="loc_2" xlink:type="locator"/>
    <link:presentationArc order="10.0" xlink:arcrole="http://www.xbrl.org/2003/arcrole/parent-child" xlink:from="loc_2" xlink:to="loc_1" xlink:type="arc"/>
    <link:loc xlink:href="../../full_ifrs-cor_2019-03-27.xsd#ifrs-full_ClassesOfCashPaymentsAbstract" xlink:label="loc_3" xlink:type="locator"/>
    <link:presentationArc order="10.0" xlink:arcrole="http://www.xbrl.org/2003/arcrole/parent-child" xlink:from="loc_1" xlink:to="loc_3" xlink:type="arc"/>
    <link:loc xlink:href="../../full_ifrs-cor_2019-03-27.xsd#ifrs-full_PaymentsToSuppliersForGoodsAndServicesAndToAndOnBehalfOfEmployees" xlink:label="loc_4" xlink:type="locator"/>
    <link:presentationArc order="10.0" xlink:arcrole="http://www.xbrl.org/2003/arcrole/parent-child" xlink:from="loc_3" xlink:to="loc_4" xlink:type="arc"/>
    <link:loc xlink:href="../../full_ifrs-cor_2019-03-27.xsd#ifrs-full_CashFlowsFromUsedInDecreaseIncreaseInRestrictedCashAndCashEquivalents" xlink:label="loc_5" xlink:type="locator"/>
    <link:loc xlink:href="../../full_ifrs-cor_2019-03-27.xsd#ifrs-full_CashFlowsFromUsedInInvestingActivitiesAbstract" xlink:label="loc_6" xlink:type="locator"/>
    <link:presentationArc order="10.0" xlink:arcrole="http://www.xbrl.org/2003/arcrole/parent-child" xlink:from="loc_6" xlink:to="loc_5" xlink:type="arc"/>
    <link:loc xlink:href="../../full_ifrs-cor_2019-03-27.xsd#ifrs-full_DividendsPaidToEquityHoldersOfParentClassifiedAsFinancingActivities" xlink:label="loc_7" xlink:type="locator"/>
    <link:loc xlink:href="../../full_ifrs-cor_2019-03-27.xsd#ifrs-full_CashFlowsFromUsedInFinancingActivitiesAbstract" xlink:label="loc_8" xlink:type="locator"/>
    <link:presentationArc order="10.0" xlink:arcrole="http://www.xbrl.org/2003/arcrole/parent-child" xlink:from="loc_8" xlink:to="loc_7" xlink:type="arc"/>
    <link:loc xlink:href="../../full_ifrs-cor_2019-03-27.xsd#ifrs-full_AdjustmentsForInterestExpense" xlink:label="loc_9" xlink:type="locator"/>
    <link:presentationArc order="20.0" xlink:arcrole="http://www.xbrl.org/2003/arcrole/parent-child" xlink:from="loc_1" xlink:to="loc_9" xlink:type="arc"/>
    <link:presentationArc order="20.0" xlink:arcrole="http://www.xbrl.org/2003/arcrole/parent-child" xlink:from="loc_2" xlink:to="loc_6" xlink:type="arc"/>
    <link:loc xlink:href="../../full_ifrs-cor_2019-03-27.xsd#ifrs-full_DividendsReceivedFromInvestmentsAccountedForUsingEquityMethodClassifiedAsInvestingActivities" xlink:label="loc_10" xlink:type="locator"/>
    <link:presentationArc order="20.0" xlink:arcrole="http://www.xbrl.org/2003/arcrole/parent-child" xlink:from="loc_6" xlink:to="loc_10" xlink:type="arc"/>
    <link:loc xlink:href="../../full_ifrs-cor_2019-03-27.xsd#ifrs-full_DividendsPaidToNoncontrollingInterestsClassifiedAsFinancingActivities" xlink:label="loc_11" xlink:type="locator"/>
    <link:presentationArc order="20.0" xlink:arcrole="http://www.xbrl.org/2003/arcrole/parent-child" xlink:from="loc_8" xlink:to="loc_11" xlink:type="arc"/>
    <link:loc xlink:href="../../full_ifrs-cor_2019-03-27.xsd#ifrs-full_PaymentsForExplorationAndEvaluationExpenses" xlink:label="loc_12" xlink:type="locator"/>
    <link:presentationArc order="20.0" xlink:arcrole="http://www.xbrl.org/2003/arcrole/parent-child" xlink:from="loc_3" xlink:to="loc_12" xlink:type="arc"/>
    <link:loc xlink:href="../../full_ifrs-cor_2019-03-27.xsd#ifrs-full_AdjustmentsForInterestIncome" xlink:label="loc_13" xlink:type="locator"/>
    <link:presentationArc order="30.0" xlink:arcrole="http://www.xbrl.org/2003/arcrole/parent-child" xlink:from="loc_1" xlink:to="loc_13" xlink:type="arc"/>
    <link:loc xlink:href="../../full_ifrs-cor_2019-03-27.xsd#ifrs-full_DividendsReceivedFromAssociatesClassifiedAsInvestingActivities" xlink:label="loc_14" xlink:type="locator"/>
    <link:presentationArc order="30.0" xlink:arcrole="http://www.xbrl.org/2003/arcrole/parent-child" xlink:from="loc_6" xlink:to="loc_14" xlink:type="arc"/>
    <link:presentationArc order="30.0" xlink:arcrole="http://www.xbrl.org/2003/arcrole/parent-child" xlink:from="loc_2" xlink:to="loc_8" xlink:type="arc"/>
    <link:loc xlink:href="../../full_ifrs-cor_2019-03-27.xsd#ifrs-full_ProceedsFromSaleOrIssueOfTreasuryShares" xlink:label="loc_15" xlink:type="locator"/>
    <link:presentationArc order="30.0" xlink:arcrole="http://www.xbrl.org/2003/arcrole/parent-child" xlink:from="loc_8" xlink:to="loc_15" xlink:type="arc"/>
    <link:loc xlink:href="../../full_ifrs-cor_2019-03-27.xsd#ifrs-full_AdjustmentsForDividendIncome" xlink:label="loc_16" xlink:type="locator"/>
    <link:presentationArc order="40.0" xlink:arcrole="http://www.xbrl.org/2003/arcrole/parent-child" xlink:from="loc_1" xlink:to="loc_16" xlink:type="arc"/>
    <link:loc xlink:href="../../full_ifrs-cor_2019-03-27.xsd#ifrs-full_DividendsReceivedFromJointVenturesClassifiedAsInvestingActivities" xlink:label="loc_17" xlink:type="locator"/>
    <link:presentationArc order="40.0" xlink:arcrole="http://www.xbrl.org/2003/arcrole/parent-child" xlink:from="loc_6" xlink:to="loc_17" xlink:type="arc"/>
    <link:loc xlink:href="../../full_ifrs-cor_2019-03-27.xsd#ifrs-full_ProceedsFromExerciseOfOptions" xlink:label="loc_18" xlink:type="locator"/>
    <link:presentationArc order="40.0" xlink:arcrole="http://www.xbrl.org/2003/arcrole/parent-child" xlink:from="loc_8" xlink:to="loc_18" xlink:type="arc"/>
    <link:loc xlink:href="../../full_ifrs-cor_2019-03-27.xsd#ifrs-full_ProceedsFromIssueOfOrdinaryShares" xlink:label="loc_19" xlink:type="locator"/>
    <link:presentationArc order="50.0" xlink:arcrole="http://www.xbrl.org/2003/arcrole/parent-child" xlink:from="loc_8" xlink:to="loc_19" xlink:type="arc"/>
    <link:loc xlink:href="../../full_ifrs-cor_2019-03-27.xsd#ifrs-full_AdjustmentsForFinanceIncome" xlink:label="loc_20" xlink:type="locator"/>
    <link:presentationArc order="50.0" xlink:arcrole="http://www.xbrl.org/2003/arcrole/parent-child" xlink:from="loc_1" xlink:to="loc_20" xlink:type="arc"/>
    <link:loc xlink:href="../../full_ifrs-cor_2019-03-27.xsd#ifrs-full_PurchaseOfInterestsInAssociates" xlink:label="loc_21" xlink:type="locator"/>
    <link:presentationArc order="50.0" xlink:arcrole="http://www.xbrl.org/2003/arcrole/parent-child" xlink:from="loc_6" xlink:to="loc_21" xlink:type="arc"/>
    <link:loc xlink:href="../../full_ifrs-cor_2019-03-27.xsd#ifrs-full_ProceedsFromIssueOfPreferenceShares" xlink:label="loc_22" xlink:type="locator"/>
    <link:presentationArc order="60.0" xlink:arcrole="http://www.xbrl.org/2003/arcrole/parent-child" xlink:from="loc_8" xlink:to="loc_22" xlink:type="arc"/>
    <link:loc xlink:href="../../full_ifrs-cor_2019-03-27.xsd#ifrs-full_AdjustmentsForFinanceIncomeCost" xlink:label="loc_23" xlink:type="locator"/>
    <link:presentationArc order="60.0" xlink:arcrole="http://www.xbrl.org/2003/arcrole/parent-child" xlink:from="loc_1" xlink:to="loc_23" xlink:type="arc"/>
    <link:loc xlink:href="../../full_ifrs-cor_2019-03-27.xsd#ifrs-full_ProceedsFromSalesOfInterestsInAssociates" xlink:label="loc_24" xlink:type="locator"/>
    <link:presentationArc order="60.0" xlink:arcrole="http://www.xbrl.org/2003/arcrole/parent-child" xlink:from="loc_6" xlink:to="loc_24" xlink:type="arc"/>
    <link:loc xlink:href="../../full_ifrs-cor_2019-03-27.xsd#ifrs-full_ProceedsFromNoncurrentBorrowings" xlink:label="loc_25" xlink:type="locator"/>
    <link:presentationArc order="70.0" xlink:arcrole="http://www.xbrl.org/2003/arcrole/parent-child" xlink:from="loc_8" xlink:to="loc_25" xlink:type="arc"/>
    <link:loc xlink:href="../../full_ifrs-cor_2019-03-27.xsd#ifrs-full_AdjustmentsForDeferredTaxExpense" xlink:label="loc_26" xlink:type="locator"/>
    <link:presentationArc order="70.0" xlink:arcrole="http://www.xbrl.org/2003/arcrole/parent-child" xlink:from="loc_1" xlink:to="loc_26" xlink:type="arc"/>
    <link:loc xlink:href="../../full_ifrs-cor_2019-03-27.xsd#ifrs-full_PurchaseOfInterestsInInvestmentsAccountedForUsingEquityMethod" xlink:label="loc_27" xlink:type="locator"/>
    <link:presentationArc order="70.0" xlink:arcrole="http://www.xbrl.org/2003/arcrole/parent-child" xlink:from="loc_6" xlink:to="loc_27" xlink:type="arc"/>
    <link:loc xlink:href="../../full_ifrs-cor_2019-03-27.xsd#ifrs-full_RepaymentsOfNoncurrentBorrowings" xlink:label="loc_28" xlink:type="locator"/>
    <link:presentationArc order="80.0" xlink:arcrole="http://www.xbrl.org/2003/arcrole/parent-child" xlink:from="loc_8" xlink:to="loc_28" xlink:type="arc"/>
    <link:loc xlink:href="../../full_ifrs-cor_2019-03-27.xsd#ifrs-full_AdjustmentsToReconcileProfitLossOtherThanChangesInWorkingCapital" xlink:label="loc_29" xlink:type="locator"/>
    <link:presentationArc order="80.0" xlink:arcrole="http://www.xbrl.org/2003/arcrole/parent-child" xlink:from="loc_1" xlink:to="loc_29" xlink:type="arc"/>
    <link:loc xlink:href="../../full_ifrs-cor_2019-03-27.xsd#ifrs-full_ProceedsFromSalesOfInvestmentsAccountedForUsingEquityMethod" xlink:label="loc_30" xlink:type="locator"/>
    <link:presentationArc order="80.0" xlink:arcrole="http://www.xbrl.org/2003/arcrole/parent-child" xlink:from="loc_6" xlink:to="loc_30" xlink:type="arc"/>
    <link:loc xlink:href="../../full_ifrs-cor_2019-03-27.xsd#ifrs-full_ProceedsFromCurrentBorrowings" xlink:label="loc_31" xlink:type="locator"/>
    <link:presentationArc order="90.0" xlink:arcrole="http://www.xbrl.org/2003/arcrole/parent-child" xlink:from="loc_8" xlink:to="loc_31" xlink:type="arc"/>
    <link:loc xlink:href="../../full_ifrs-cor_2019-03-27.xsd#ifrs-full_CashFlowsFromUsedInOperationsBeforeChangesInWorkingCapital" xlink:label="loc_32" xlink:type="locator"/>
    <link:presentationArc order="90.0" xlink:arcrole="http://www.xbrl.org/2003/arcrole/parent-child" xlink:from="loc_1" xlink:to="loc_32" xlink:type="arc"/>
    <link:loc xlink:href="../../full_ifrs-cor_2019-03-27.xsd#ifrs-full_CashAdvancesAndLoansMadeToRelatedParties" xlink:label="loc_33" xlink:type="locator"/>
    <link:presentationArc order="90.0" xlink:arcrole="http://www.xbrl.org/2003/arcrole/parent-child" xlink:from="loc_6" xlink:to="loc_33" xlink:type="arc"/>
    <link:loc xlink:href="../../full_ifrs-cor_2019-03-27.xsd#ifrs-full_RepaymentsOfCurrentBorrowings" xlink:label="loc_34" xlink:type="locator"/>
    <link:presentationArc order="100.0" xlink:arcrole="http://www.xbrl.org/2003/arcrole/parent-child" xlink:from="loc_8" xlink:to="loc_34" xlink:type="arc"/>
    <link:loc xlink:href="../../full_ifrs-cor_2019-03-27.xsd#ifrs-full_IncreaseDecreaseInWorkingCapital" xlink:label="loc_35" xlink:type="locator"/>
    <link:presentationArc order="100.0" xlink:arcrole="http://www.xbrl.org/2003/arcrole/parent-child" xlink:from="loc_1" xlink:to="loc_35" xlink:type="arc"/>
    <link:loc xlink:href="../../full_ifrs-cor_2019-03-27.xsd#ifrs-full_CashReceiptsFromRepaymentOfAdvancesAndLoansMadeToRelatedParties" xlink:label="loc_36" xlink:type="locator"/>
    <link:presentationArc order="100.0" xlink:arcrole="http://www.xbrl.org/2003/arcrole/parent-child" xlink:from="loc_6" xlink:to="loc_36" xlink:type="arc"/>
    <link:loc xlink:href="../../full_ifrs-cor_2019-03-27.xsd#ifrs-full_CashFlowsFromUsedInIncreaseDecreaseInCurrentBorrowings" xlink:label="loc_37" xlink:type="locator"/>
    <link:presentationArc order="110.0" xlink:arcrole="http://www.xbrl.org/2003/arcrole/parent-child" xlink:from="loc_8" xlink:to="loc_37" xlink:type="arc"/>
    <link:loc xlink:href="../../full_ifrs-cor_2019-03-27.xsd#ifrs-full_AdjustmentsForDecreaseIncreaseInTradeAndOtherReceivables" xlink:label="loc_38" xlink:type="locator"/>
    <link:presentationArc order="110.0" xlink:arcrole="http://www.xbrl.org/2003/arcrole/parent-child" xlink:from="loc_1" xlink:to="loc_38" xlink:type="arc"/>
    <link:loc xlink:href="../../full_ifrs-cor_2019-03-27.xsd#ifrs-full_PurchaseOfInvestmentProperty" xlink:label="loc_39" xlink:type="locator"/>
    <link:presentationArc order="110.0" xlink:arcrole="http://www.xbrl.org/2003/arcrole/parent-child" xlink:from="loc_6" xlink:to="loc_39" xlink:type="arc"/>
    <link:loc xlink:href="../../full_ifrs-cor_2019-03-27.xsd#ifrs-full_CashAdvancesAndLoansFromRelatedParties" xlink:label="loc_40" xlink:type="locator"/>
    <link:presentationArc order="120.0" xlink:arcrole="http://www.xbrl.org/2003/arcrole/parent-child" xlink:from="loc_8" xlink:to="loc_40" xlink:type="arc"/>
    <link:loc xlink:href="../../full_ifrs-cor_2019-03-27.xsd#ifrs-full_AdjustmentsForIncreaseDecreaseInTradeAndOtherPayables" xlink:label="loc_41" xlink:type="locator"/>
    <link:presentationArc order="120.0" xlink:arcrole="http://www.xbrl.org/2003/arcrole/parent-child" xlink:from="loc_1" xlink:to="loc_41" xlink:type="arc"/>
    <link:loc xlink:href="../../full_ifrs-cor_2019-03-27.xsd#ifrs-full_ProceedsFromSalesOfInvestmentProperty" xlink:label="loc_42" xlink:type="locator"/>
    <link:presentationArc order="120.0" xlink:arcrole="http://www.xbrl.org/2003/arcrole/parent-child" xlink:from="loc_6" xlink:to="loc_42" xlink:type="arc"/>
    <link:loc xlink:href="../../full_ifrs-cor_2019-03-27.xsd#ifrs-full_CashRepaymentsOfAdvancesAndLoansFromRelatedParties" xlink:label="loc_43" xlink:type="locator"/>
    <link:presentationArc order="130.0" xlink:arcrole="http://www.xbrl.org/2003/arcrole/parent-child" xlink:from="loc_8" xlink:to="loc_43" xlink:type="arc"/>
    <link:loc xlink:href="../../full_ifrs-cor_2019-03-27.xsd#ifrs-full_AdjustmentsForDecreaseIncreaseInOtherAssets" xlink:label="loc_44" xlink:type="locator"/>
    <link:presentationArc order="130.0" xlink:arcrole="http://www.xbrl.org/2003/arcrole/parent-child" xlink:from="loc_1" xlink:to="loc_44" xlink:type="arc"/>
    <link:loc xlink:href="../../full_ifrs-cor_2019-03-27.xsd#ifrs-full_PurchaseOfBiologicalAssets" xlink:label="loc_45" xlink:type="locator"/>
    <link:presentationArc order="130.0" xlink:arcrole="http://www.xbrl.org/2003/arcrole/parent-child" xlink:from="loc_6" xlink:to="loc_45" xlink:type="arc"/>
    <link:loc xlink:href="../../full_ifrs-cor_2019-03-27.xsd#ifrs-full_ProceedsFromIssueOfBondsNotesAndDebentures" xlink:label="loc_46" xlink:type="locator"/>
    <link:presentationArc order="140.0" xlink:arcrole="http://www.xbrl.org/2003/arcrole/parent-child" xlink:from="loc_8" xlink:to="loc_46" xlink:type="arc"/>
    <link:loc xlink:href="../../full_ifrs-cor_2019-03-27.xsd#ifrs-full_AdjustmentsForIncreaseDecreaseInOtherLiabilities" xlink:label="loc_47" xlink:type="locator"/>
    <link:presentationArc order="140.0" xlink:arcrole="http://www.xbrl.org/2003/arcrole/parent-child" xlink:from="loc_1" xlink:to="loc_47" xlink:type="arc"/>
    <link:loc xlink:href="../../full_ifrs-cor_2019-03-27.xsd#ifrs-full_ProceedsFromSalesOfBiologicalAssets" xlink:label="loc_48" xlink:type="locator"/>
    <link:presentationArc order="140.0" xlink:arcrole="http://www.xbrl.org/2003/arcrole/parent-child" xlink:from="loc_6" xlink:to="loc_48" xlink:type="arc"/>
    <link:loc xlink:href="../../full_ifrs-cor_2019-03-27.xsd#ifrs-full_RepaymentsOfBondsNotesAndDebentures" xlink:label="loc_49" xlink:type="locator"/>
    <link:presentationArc order="150.0" xlink:arcrole="http://www.xbrl.org/2003/arcrole/parent-child" xlink:from="loc_8" xlink:to="loc_49" xlink:type="arc"/>
    <link:loc xlink:href="../../full_ifrs-cor_2019-03-27.xsd#ifrs-full_PurchaseOfExplorationAndEvaluationAssets" xlink:label="loc_50" xlink:type="locator"/>
    <link:presentationArc order="150.0" xlink:arcrole="http://www.xbrl.org/2003/arcrole/parent-child" xlink:from="loc_6" xlink:to="loc_50" xlink:type="arc"/>
    <link:loc xlink:href="../../full_ifrs-cor_2019-03-27.xsd#ifrs-full_AdjustmentsForDecreaseIncreaseInOtherCurrentAssets" xlink:label="loc_51" xlink:type="locator"/>
    <link:presentationArc order="150.0" xlink:arcrole="http://www.xbrl.org/2003/arcrole/parent-child" xlink:from="loc_1" xlink:to="loc_51" xlink:type="arc"/>
    <link:loc xlink:href="../../full_ifrs-cor_2019-03-27.xsd#ifrs-full_PaymentsForShareIssueCosts" xlink:label="loc_52" xlink:type="locator"/>
    <link:presentationArc order="160.0" xlink:arcrole="http://www.xbrl.org/2003/arcrole/parent-child" xlink:from="loc_8" xlink:to="loc_52" xlink:type="arc"/>
    <link:loc xlink:href="../../full_ifrs-cor_2019-03-27.xsd#ifrs-full_ProceedsFromDisposalOfExplorationAndEvaluationAssets" xlink:label="loc_53" xlink:type="locator"/>
    <link:presentationArc order="160.0" xlink:arcrole="http://www.xbrl.org/2003/arcrole/parent-child" xlink:from="loc_6" xlink:to="loc_53" xlink:type="arc"/>
    <link:loc xlink:href="../../full_ifrs-cor_2019-03-27.xsd#ifrs-full_AdjustmentsForIncreaseDecreaseInOtherCurrentLiabilities" xlink:label="loc_54" xlink:type="locator"/>
    <link:presentationArc order="160.0" xlink:arcrole="http://www.xbrl.org/2003/arcrole/parent-child" xlink:from="loc_1" xlink:to="loc_54" xlink:type="arc"/>
    <link:loc xlink:href="../../full_ifrs-cor_2019-03-27.xsd#ifrs-full_PaymentsForDebtIssueCosts" xlink:label="loc_55" xlink:type="locator"/>
    <link:presentationArc order="170.0" xlink:arcrole="http://www.xbrl.org/2003/arcrole/parent-child" xlink:from="loc_8" xlink:to="loc_55" xlink:type="arc"/>
    <link:loc xlink:href="../../full_ifrs-cor_2019-03-27.xsd#ifrs-full_PurchaseOfMiningAssets" xlink:label="loc_56" xlink:type="locator"/>
    <link:presentationArc order="170.0" xlink:arcrole="http://www.xbrl.org/2003/arcrole/parent-child" xlink:from="loc_6" xlink:to="loc_56" xlink:type="arc"/>
    <link:loc xlink:href="../../full_ifrs-cor_2019-03-27.xsd#ifrs-full_AdjustmentsForIncreaseDecreaseInEmployeeBenefitLiabilities" xlink:label="loc_57" xlink:type="locator"/>
    <link:presentationArc order="170.0" xlink:arcrole="http://www.xbrl.org/2003/arcrole/parent-child" xlink:from="loc_1" xlink:to="loc_57" xlink:type="arc"/>
    <link:loc xlink:href="../../full_ifrs-cor_2019-03-27.xsd#ifrs-full_ProceedsFromContributionsOfNoncontrollingInterests" xlink:label="loc_58" xlink:type="locator"/>
    <link:presentationArc order="180.0" xlink:arcrole="http://www.xbrl.org/2003/arcrole/parent-child" xlink:from="loc_8" xlink:to="loc_58" xlink:type="arc"/>
    <link:loc xlink:href="../../full_ifrs-cor_2019-03-27.xsd#ifrs-full_ProceedsFromDisposalOfMiningAssets" xlink:label="loc_59" xlink:type="locator"/>
    <link:presentationArc order="180.0" xlink:arcrole="http://www.xbrl.org/2003/arcrole/parent-child" xlink:from="loc_6" xlink:to="loc_59" xlink:type="arc"/>
    <link:loc xlink:href="../../full_ifrs-cor_2019-03-27.xsd#ifrs-full_AdjustmentsForDecreaseIncreaseInLoansAndAdvancesToCustomers" xlink:label="loc_60" xlink:type="locator"/>
    <link:presentationArc order="180.0" xlink:arcrole="http://www.xbrl.org/2003/arcrole/parent-child" xlink:from="loc_1" xlink:to="loc_60" xlink:type="arc"/>
    <link:loc xlink:href="../../full_ifrs-cor_2019-03-27.xsd#ifrs-full_ProceedsFromIssueOfSubordinatedLiabilities" xlink:label="loc_61" xlink:type="locator"/>
    <link:presentationArc order="190.0" xlink:arcrole="http://www.xbrl.org/2003/arcrole/parent-child" xlink:from="loc_8" xlink:to="loc_61" xlink:type="arc"/>
    <link:loc xlink:href="../../full_ifrs-cor_2019-03-27.xsd#ifrs-full_PurchaseOfOilAndGasAssets" xlink:label="loc_62" xlink:type="locator"/>
    <link:presentationArc order="190.0" xlink:arcrole="http://www.xbrl.org/2003/arcrole/parent-child" xlink:from="loc_6" xlink:to="loc_62" xlink:type="arc"/>
    <link:loc xlink:href="../../full_ifrs-cor_2019-03-27.xsd#ifrs-full_AdjustmentsForDecreaseIncreaseInLoansAndAdvancesToBanks" xlink:label="loc_63" xlink:type="locator"/>
    <link:presentationArc order="190.0" xlink:arcrole="http://www.xbrl.org/2003/arcrole/parent-child" xlink:from="loc_1" xlink:to="loc_63" xlink:type="arc"/>
    <link:loc xlink:href="../../full_ifrs-cor_2019-03-27.xsd#ifrs-full_RepaymentsOfSubordinatedLiabilities" xlink:label="loc_64" xlink:type="locator"/>
    <link:presentationArc order="200.0" xlink:arcrole="http://www.xbrl.org/2003/arcrole/parent-child" xlink:from="loc_8" xlink:to="loc_64" xlink:type="arc"/>
    <link:loc xlink:href="../../full_ifrs-cor_2019-03-27.xsd#ifrs-full_ProceedsFromDisposalOfOilAndGasAssets" xlink:label="loc_65" xlink:type="locator"/>
    <link:presentationArc order="200.0" xlink:arcrole="http://www.xbrl.org/2003/arcrole/parent-child" xlink:from="loc_6" xlink:to="loc_65" xlink:type="arc"/>
    <link:loc xlink:href="../../full_ifrs-cor_2019-03-27.xsd#ifrs-full_AdjustmentsForIncreaseDecreaseInDepositsFromCustomers" xlink:label="loc_66" xlink:type="locator"/>
    <link:presentationArc order="200.0" xlink:arcrole="http://www.xbrl.org/2003/arcrole/parent-child" xlink:from="loc_1" xlink:to="loc_66" xlink:type="arc"/>
    <link:loc xlink:href="../../full_ifrs-cor_2019-03-27.xsd#ifrs-full_ProceedsFromDisposalOfNoncurrentAssetsOrDisposalGroupsClassifiedAsHeldForSaleAndDiscontinuedOperations" xlink:label="loc_67" xlink:type="locator"/>
    <link:presentationArc order="210.0" xlink:arcrole="http://www.xbrl.org/2003/arcrole/parent-child" xlink:from="loc_6" xlink:to="loc_67" xlink:type="arc"/>
    <link:loc xlink:href="../../full_ifrs-cor_2019-03-27.xsd#ifrs-full_AdjustmentsForIncreaseDecreaseInDepositsFromBanks" xlink:label="loc_68" xlink:type="locator"/>
    <link:presentationArc order="210.0" xlink:arcrole="http://www.xbrl.org/2003/arcrole/parent-child" xlink:from="loc_1" xlink:to="loc_68" xlink:type="arc"/>
    <link:loc xlink:href="../../full_ifrs-cor_2019-03-27.xsd#ifrs-full_PurchaseOfPropertyPlantAndEquipmentIntangibleAssetsOtherThanGoodwillInvestmentPropertyAndOtherNoncurrentAssets" xlink:label="loc_69" xlink:type="locator"/>
    <link:presentationArc order="220.0" xlink:arcrole="http://www.xbrl.org/2003/arcrole/parent-child" xlink:from="loc_6" xlink:to="loc_69" xlink:type="arc"/>
    <link:loc xlink:href="../../full_ifrs-cor_2019-03-27.xsd#ifrs-full_AdjustmentsForIncreaseDecreaseInInsuranceReinsuranceAndInvestmentContractLiabilities" xlink:label="loc_70" xlink:type="locator"/>
    <link:presentationArc order="220.0" xlink:arcrole="http://www.xbrl.org/2003/arcrole/parent-child" xlink:from="loc_1" xlink:to="loc_70" xlink:type="arc"/>
    <link:loc xlink:href="../../full_ifrs-cor_2019-03-27.xsd#ifrs-full_AdjustmentsForIncreaseDecreaseInRepurchaseAgreementsAndCashCollateralOnSecuritiesLent" xlink:label="loc_71" xlink:type="locator"/>
    <link:presentationArc order="230.0" xlink:arcrole="http://www.xbrl.org/2003/arcrole/parent-child" xlink:from="loc_1" xlink:to="loc_71" xlink:type="arc"/>
    <link:loc xlink:href="../../full_ifrs-cor_2019-03-27.xsd#ifrs-full_ProceedsFromDisposalsOfPropertyPlantAndEquipmentIntangibleAssetsOtherThanGoodwillInvestmentPropertyAndOtherNoncurrentAssets" xlink:label="loc_72" xlink:type="locator"/>
    <link:presentationArc order="230.0" xlink:arcrole="http://www.xbrl.org/2003/arcrole/parent-child" xlink:from="loc_6" xlink:to="loc_72" xlink:type="arc"/>
    <link:loc xlink:href="../../full_ifrs-cor_2019-03-27.xsd#ifrs-full_AdjustmentsForDecreaseIncreaseInReverseRepurchaseAgreementsAndCashCollateralOnSecuritiesBorrowed" xlink:label="loc_73" xlink:type="locator"/>
    <link:presentationArc order="240.0" xlink:arcrole="http://www.xbrl.org/2003/arcrole/parent-child" xlink:from="loc_1" xlink:to="loc_73" xlink:type="arc"/>
    <link:loc xlink:href="../../full_ifrs-cor_2019-03-27.xsd#ifrs-full_PaymentsForDevelopmentProjectExpenditure" xlink:label="loc_74" xlink:type="locator"/>
    <link:presentationArc order="240.0" xlink:arcrole="http://www.xbrl.org/2003/arcrole/parent-child" xlink:from="loc_6" xlink:to="loc_74" xlink:type="arc"/>
    <link:loc xlink:href="../../full_ifrs-cor_2019-03-27.xsd#ifrs-full_AdjustmentsForDecreaseIncreaseInFinancialAssetsHeldForTrading" xlink:label="loc_75" xlink:type="locator"/>
    <link:presentationArc order="250.0" xlink:arcrole="http://www.xbrl.org/2003/arcrole/parent-child" xlink:from="loc_1" xlink:to="loc_75" xlink:type="arc"/>
    <link:loc xlink:href="../../full_ifrs-cor_2019-03-27.xsd#ifrs-full_CashFlowsUsedInExplorationAndDevelopmentActivities" xlink:label="loc_76" xlink:type="locator"/>
    <link:presentationArc order="250.0" xlink:arcrole="http://www.xbrl.org/2003/arcrole/parent-child" xlink:from="loc_6" xlink:to="loc_76" xlink:type="arc"/>
    <link:loc xlink:href="../../full_ifrs-cor_2019-03-27.xsd#ifrs-full_AdjustmentsForIncreaseDecreaseInFinancialLiabilitiesHeldForTrading" xlink:label="loc_77" xlink:type="locator"/>
    <link:presentationArc order="260.0" xlink:arcrole="http://www.xbrl.org/2003/arcrole/parent-child" xlink:from="loc_1" xlink:to="loc_77" xlink:type="arc"/>
    <link:loc xlink:href="../../full_ifrs-cor_2019-03-27.xsd#ifrs-full_PurchaseOfInvestmentsOtherThanInvestmentsAccountedForUsingEquityMethod" xlink:label="loc_78" xlink:type="locator"/>
    <link:presentationArc order="260.0" xlink:arcrole="http://www.xbrl.org/2003/arcrole/parent-child" xlink:from="loc_6" xlink:to="loc_78" xlink:type="arc"/>
    <link:loc xlink:href="../../full_ifrs-cor_2019-03-27.xsd#ifrs-full_AdjustmentsForDecreaseIncreaseInDerivativeFinancialAssets" xlink:label="loc_79" xlink:type="locator"/>
    <link:presentationArc order="270.0" xlink:arcrole="http://www.xbrl.org/2003/arcrole/parent-child" xlink:from="loc_1" xlink:to="loc_79" xlink:type="arc"/>
    <link:loc xlink:href="../../full_ifrs-cor_2019-03-27.xsd#ifrs-full_ProceedsFromSalesOfInvestmentsOtherThanInvestmentsAccountedForUsingEquityMethod" xlink:label="loc_80" xlink:type="locator"/>
    <link:presentationArc order="270.0" xlink:arcrole="http://www.xbrl.org/2003/arcrole/parent-child" xlink:from="loc_6" xlink:to="loc_80" xlink:type="arc"/>
    <link:loc xlink:href="../../full_ifrs-cor_2019-03-27.xsd#ifrs-full_AdjustmentsForIncreaseDecreaseInDerivativeFinancialLiabilities" xlink:label="loc_81" xlink:type="locator"/>
    <link:presentationArc order="280.0" xlink:arcrole="http://www.xbrl.org/2003/arcrole/parent-child" xlink:from="loc_1" xlink:to="loc_81" xlink:type="arc"/>
    <link:loc xlink:href="../../full_ifrs-cor_2019-03-27.xsd#ifrs-full_PurchaseOfFinancialInstrumentsClassifiedAsInvestingActivities" xlink:label="loc_82" xlink:type="locator"/>
    <link:presentationArc order="280.0" xlink:arcrole="http://www.xbrl.org/2003/arcrole/parent-child" xlink:from="loc_6" xlink:to="loc_82" xlink:type="arc"/>
    <link:loc xlink:href="../../full_ifrs-cor_2019-03-27.xsd#ifrs-full_AdjustmentsForDecreaseIncreaseInBiologicalAssets" xlink:label="loc_83" xlink:type="locator"/>
    <link:presentationArc order="290.0" xlink:arcrole="http://www.xbrl.org/2003/arcrole/parent-child" xlink:from="loc_1" xlink:to="loc_83" xlink:type="arc"/>
    <link:loc xlink:href="../../full_ifrs-cor_2019-03-27.xsd#ifrs-full_ProceedsFromSalesOrMaturityOfFinancialInstrumentsClassifiedAsInvestingActivities" xlink:label="loc_84" xlink:type="locator"/>
    <link:presentationArc order="290.0" xlink:arcrole="http://www.xbrl.org/2003/arcrole/parent-child" xlink:from="loc_6" xlink:to="loc_84" xlink:type="arc"/>
    <link:loc xlink:href="../../full_ifrs-cor_2019-03-27.xsd#ifrs-full_AdjustmentsForIncreaseInOtherProvisionsArisingFromPassageOfTime" xlink:label="loc_85" xlink:type="locator"/>
    <link:presentationArc order="300.0" xlink:arcrole="http://www.xbrl.org/2003/arcrole/parent-child" xlink:from="loc_1" xlink:to="loc_85" xlink:type="arc"/>
    <link:loc xlink:href="../../full_ifrs-cor_2019-03-27.xsd#ifrs-full_PurchaseOfAvailableforsaleFinancialAssets" xlink:label="loc_86" xlink:type="locator"/>
    <link:presentationArc order="300.0" xlink:arcrole="http://www.xbrl.org/2003/arcrole/parent-child" xlink:from="loc_6" xlink:to="loc_86" xlink:type="arc"/>
    <link:loc xlink:href="../../full_ifrs-cor_2019-03-27.xsd#ifrs-full_AdjustmentsForDepreciationAndAmortisationExpenseAndImpairmentLossReversalOfImpairmentLossRecognisedInProfitOrLoss" xlink:label="loc_87" xlink:type="locator"/>
    <link:presentationArc order="310.0" xlink:arcrole="http://www.xbrl.org/2003/arcrole/parent-child" xlink:from="loc_1" xlink:to="loc_87" xlink:type="arc"/>
    <link:loc xlink:href="../../full_ifrs-cor_2019-03-27.xsd#ifrs-full_ProceedsFromDisposalOrMaturityOfAvailableforsaleFinancialAssets" xlink:label="loc_88" xlink:type="locator"/>
    <link:presentationArc order="310.0" xlink:arcrole="http://www.xbrl.org/2003/arcrole/parent-child" xlink:from="loc_6" xlink:to="loc_88" xlink:type="arc"/>
    <link:loc xlink:href="../../full_ifrs-cor_2019-03-27.xsd#ifrs-full_AdjustmentsForAmortisationExpense" xlink:label="loc_89" xlink:type="locator"/>
    <link:presentationArc order="320.0" xlink:arcrole="http://www.xbrl.org/2003/arcrole/parent-child" xlink:from="loc_1" xlink:to="loc_89" xlink:type="arc"/>
    <link:loc xlink:href="../../full_ifrs-cor_2019-03-27.xsd#ifrs-full_CashFlowsFromUsedInDecreaseIncreaseInShorttermDepositsAndInvestments" xlink:label="loc_90" xlink:type="locator"/>
    <link:presentationArc order="320.0" xlink:arcrole="http://www.xbrl.org/2003/arcrole/parent-child" xlink:from="loc_6" xlink:to="loc_90" xlink:type="arc"/>
    <link:loc xlink:href="../../full_ifrs-cor_2019-03-27.xsd#ifrs-full_AdjustmentsForDepreciationExpense" xlink:label="loc_91" xlink:type="locator"/>
    <link:presentationArc order="330.0" xlink:arcrole="http://www.xbrl.org/2003/arcrole/parent-child" xlink:from="loc_1" xlink:to="loc_91" xlink:type="arc"/>
    <link:loc xlink:href="../../full_ifrs-cor_2019-03-27.xsd#ifrs-full_InflowsOfCashFromInvestingActivities" xlink:label="loc_92" xlink:type="locator"/>
    <link:presentationArc order="330.0" xlink:arcrole="http://www.xbrl.org/2003/arcrole/parent-child" xlink:from="loc_6" xlink:to="loc_92" xlink:type="arc"/>
    <link:loc xlink:href="../../full_ifrs-cor_2019-03-27.xsd#ifrs-full_AdjustmentsForImpairmentLossRecognisedInProfitOrLossGoodwill" xlink:label="loc_93" xlink:type="locator"/>
    <link:presentationArc order="340.0" xlink:arcrole="http://www.xbrl.org/2003/arcrole/parent-child" xlink:from="loc_1" xlink:to="loc_93" xlink:type="arc"/>
    <link:loc xlink:href="../../full_ifrs-cor_2019-03-27.xsd#ifrs-full_OutflowsOfCashFromInvestingActivities" xlink:label="loc_94" xlink:type="locator"/>
    <link:presentationArc order="340.0" xlink:arcrole="http://www.xbrl.org/2003/arcrole/parent-child" xlink:from="loc_6" xlink:to="loc_94" xlink:type="arc"/>
    <link:loc xlink:href="../../full_ifrs-cor_2019-03-27.xsd#ifrs-full_AdjustmentsForImpairmentLossReversalOfImpairmentLossRecognisedInProfitOrLossTradeAndOtherReceivables" xlink:label="loc_95" xlink:type="locator"/>
    <link:presentationArc order="350.0" xlink:arcrole="http://www.xbrl.org/2003/arcrole/parent-child" xlink:from="loc_1" xlink:to="loc_95" xlink:type="arc"/>
    <link:loc xlink:href="../../full_ifrs-cor_2019-03-27.xsd#ifrs-full_AdjustmentsForImpairmentLossReversalOfImpairmentLossRecognisedInProfitOrLossInventories" xlink:label="loc_96" xlink:type="locator"/>
    <link:presentationArc order="360.0" xlink:arcrole="http://www.xbrl.org/2003/arcrole/parent-child" xlink:from="loc_1" xlink:to="loc_96" xlink:type="arc"/>
    <link:loc xlink:href="../../full_ifrs-cor_2019-03-27.xsd#ifrs-full_AdjustmentsForImpairmentLossReversalOfImpairmentLossRecognisedInProfitOrLossPropertyPlantAndEquipment" xlink:label="loc_97" xlink:type="locator"/>
    <link:presentationArc order="370.0" xlink:arcrole="http://www.xbrl.org/2003/arcrole/parent-child" xlink:from="loc_1" xlink:to="loc_97" xlink:type="arc"/>
    <link:loc xlink:href="../../full_ifrs-cor_2019-03-27.xsd#ifrs-full_AdjustmentsForImpairmentLossReversalOfImpairmentLossRecognisedInProfitOrLossExplorationAndEvaluationAssets" xlink:label="loc_98" xlink:type="locator"/>
    <link:presentationArc order="380.0" xlink:arcrole="http://www.xbrl.org/2003/arcrole/parent-child" xlink:from="loc_1" xlink:to="loc_98" xlink:type="arc"/>
    <link:loc xlink:href="../../full_ifrs-cor_2019-03-27.xsd#ifrs-full_AdjustmentsForImpairmentLossReversalOfImpairmentLossRecognisedInProfitOrLossLoansAndAdvances" xlink:label="loc_99" xlink:type="locator"/>
    <link:presentationArc order="390.0" xlink:arcrole="http://www.xbrl.org/2003/arcrole/parent-child" xlink:from="loc_1" xlink:to="loc_99" xlink:type="arc"/>
    <link:loc xlink:href="../../full_ifrs-cor_2019-03-27.xsd#ifrs-full_AdjustmentsForGainsLossesOnFairValueAdjustmentInvestmentProperty" xlink:label="loc_100" xlink:type="locator"/>
    <link:presentationArc order="400.0" xlink:arcrole="http://www.xbrl.org/2003/arcrole/parent-child" xlink:from="loc_1" xlink:to="loc_100" xlink:type="arc"/>
    <link:loc xlink:href="../../full_ifrs-cor_2019-03-27.xsd#ifrs-full_AdjustmentsForGainsLossesOnChangeInFairValueLessCostsToSellBiologicalAssets" xlink:label="loc_101" xlink:type="locator"/>
    <link:presentationArc order="410.0" xlink:arcrole="http://www.xbrl.org/2003/arcrole/parent-child" xlink:from="loc_1" xlink:to="loc_101" xlink:type="arc"/>
    <link:loc xlink:href="../../full_ifrs-cor_2019-03-27.xsd#ifrs-full_AdjustmentsForGainsLossesOnChangeInFairValueOfDerivatives" xlink:label="loc_102" xlink:type="locator"/>
    <link:presentationArc order="420.0" xlink:arcrole="http://www.xbrl.org/2003/arcrole/parent-child" xlink:from="loc_1" xlink:to="loc_102" xlink:type="arc"/>
    <link:loc xlink:href="../../full_ifrs-cor_2019-03-27.xsd#ifrs-full_AdjustmentsForGainLossOnDisposalsPropertyPlantAndEquipment" xlink:label="loc_103" xlink:type="locator"/>
    <link:presentationArc order="430.0" xlink:arcrole="http://www.xbrl.org/2003/arcrole/parent-child" xlink:from="loc_1" xlink:to="loc_103" xlink:type="arc"/>
    <link:loc xlink:href="../../full_ifrs-cor_2019-03-27.xsd#ifrs-full_AdjustmentsForGainLossOnDisposalOfInvestmentsInSubsidiariesJointVenturesAndAssociates" xlink:label="loc_104" xlink:type="locator"/>
    <link:presentationArc order="440.0" xlink:arcrole="http://www.xbrl.org/2003/arcrole/parent-child" xlink:from="loc_1" xlink:to="loc_104" xlink:type="arc"/>
    <link:loc xlink:href="../../full_ifrs-cor_2019-03-27.xsd#ifrs-full_AdjustmentsForUndistributedProfitsOfInvestmentsAccountedForUsingEquityMethod" xlink:label="loc_105" xlink:type="locator"/>
    <link:presentationArc order="450.0" xlink:arcrole="http://www.xbrl.org/2003/arcrole/parent-child" xlink:from="loc_1" xlink:to="loc_105" xlink:type="arc"/>
    <link:loc xlink:href="../../full_ifrs-cor_2019-03-27.xsd#ifrs-full_AdjustmentsForIncreaseDecreaseInDeferredIncome" xlink:label="loc_106" xlink:type="locator"/>
    <link:presentationArc order="460.0" xlink:arcrole="http://www.xbrl.org/2003/arcrole/parent-child" xlink:from="loc_1" xlink:to="loc_106" xlink:type="arc"/>
    <link:loc xlink:href="../../full_ifrs-cor_2019-03-27.xsd#ifrs-full_IncomeTaxesPaidClassifiedAsOperatingActivities" xlink:label="loc_107" xlink:type="locator"/>
    <link:presentationArc order="470.0" xlink:arcrole="http://www.xbrl.org/2003/arcrole/parent-child" xlink:from="loc_1" xlink:to="loc_107" xlink:type="arc"/>
    <link:loc xlink:href="../../full_ifrs-cor_2019-03-27.xsd#ifrs-full_IncomeTaxesRefundClassifiedAsOperatingActivities" xlink:label="loc_108" xlink:type="locator"/>
    <link:presentationArc order="480.0" xlink:arcrole="http://www.xbrl.org/2003/arcrole/parent-child" xlink:from="loc_1" xlink:to="loc_108" xlink:type="arc"/>
    <link:loc xlink:href="../../full_ifrs-cor_2019-03-27.xsd#ifrs-full_FinanceCostsPaidClassifiedAsOperatingActivities" xlink:label="loc_109" xlink:type="locator"/>
    <link:presentationArc order="490.0" xlink:arcrole="http://www.xbrl.org/2003/arcrole/parent-child" xlink:from="loc_1" xlink:to="loc_109" xlink:type="arc"/>
    <link:loc xlink:href="../../full_ifrs-cor_2019-03-27.xsd#ifrs-full_FinanceIncomeReceivedClassifiedAsOperatingActivities" xlink:label="loc_110" xlink:type="locator"/>
    <link:presentationArc order="500.0" xlink:arcrole="http://www.xbrl.org/2003/arcrole/parent-child" xlink:from="loc_1" xlink:to="loc_110" xlink:type="arc"/>
  </link:presentationLink>
</link:linkbase>
